test_pypkg/__init__.py
test_pypkg/__main__.py
test_pypkg/hello.py
test_pypkg-1.2.dist-info/METADATA
test_pypkg-1.2.dist-info/WHEEL
test_pypkg-1.2.dist-info/top_level.txt
test_pypkg-1.2.dist-info/RECORD
