Metadata-Version: 2.1
Name: test-pypkg
Version: 1.2
Summary: A test python packaging
Home-page: UNKNOWN
Author: Sangram Keshari Sahu
Author-email: sangram@bionivid.com
License: UNKNOWN
Platform: UNKNOWN
Requires-Python: >=3.5
Requires-Dist: numpy
Requires-Dist: pandas
